base36.py
base36-0.1.0.dist-info/DESCRIPTION.rst
base36-0.1.0.dist-info/METADATA
base36-0.1.0.dist-info/metadata.json
base36-0.1.0.dist-info/RECORD
base36-0.1.0.dist-info/top_level.txt
base36-0.1.0.dist-info/WHEEL
