Metadata-Version: 2.0
Name: base36
Version: 0.1.0
Summary: Yet another implementation for the positional numeral system using 36 as the radix.
Home-page: https://github.com/tonyseek/python-base36
Author: Jiangge Zhang
Author-email: tonyseek@gmail.com
License: MIT
Platform: Any
Classifier: Development Status :: 3 - Alpha
Classifier: License :: OSI Approved :: MIT License
Classifier: Operating System :: OS Independent
Classifier: Programming Language :: Python
Classifier: Programming Language :: Python :: 2.7
Classifier: Programming Language :: Python :: 3.3
Classifier: Programming Language :: Python :: 3.4
Classifier: Programming Language :: Python :: Implementation :: PyPy
